README.md
dlq_redeem/__init__.py
dlq_redeem/cli.py
dlq_redeem/commands.py
dlq_redeem/process_dlq.py
dlq_redeem/queue.py
dlq_redeem/utils.py
dlq_redeem-0.0.1.dist-info/entry_points.txt
dlq_redeem-0.0.1.dist-info/LICENSE
dlq_redeem-0.0.1.dist-info/WHEEL
dlq_redeem-0.0.1.dist-info/METADATA
dlq_redeem-0.0.1.dist-info/RECORD
