Metadata-Version: 2.1
Name: dlq-redeem
Version: 0.0.1
Summary: AWS SQS dead letter queue (DLQ) message inspection and cleanup automation tool
Home-page: https://github.com/epsylabs/dlq-redeem
License: MIT
Keywords: library,aws
Author: Epsy
Author-email: engineering@epsyhealth.com
Requires-Python: >=3.7,<4.0
Classifier: Intended Audience :: Developers
Classifier: License :: OSI Approved :: MIT License
Classifier: Programming Language :: Python
Classifier: Programming Language :: Python :: 3
Classifier: Programming Language :: Python :: 3 :: Only
Classifier: Programming Language :: Python :: 3.7
Classifier: Programming Language :: Python :: 3.8
Classifier: Programming Language :: Python :: 3.9
Requires-Dist: boto3 (>=1.23,<2.0)
Requires-Dist: click (>=8.1.3,<9.0.0)
Requires-Dist: click-log (>=0.4.0,<0.5.0)
Project-URL: Repository, https://github.com/epsylabs/dlq-redeem
